api/__init__.py
api/api_interface.py
api/config_api_interface.py
api/etherscan_api_interface.py
api/transaction_api_interface.py
checker/__init__.py
checker/checker.py
tests/__init__.py
tests/api/__init__.py
tests/api/test_config_api_interface.py
tests/api/test_transaction_api_interface.py
tests/checker/__init__.py
tests/checker/test_checker.py
transaction_indexer_quality_checker-0.0.2.dist-info/METADATA
transaction_indexer_quality_checker-0.0.2.dist-info/WHEEL
transaction_indexer_quality_checker-0.0.2.dist-info/top_level.txt
transaction_indexer_quality_checker-0.0.2.dist-info/RECORD
