Metadata-Version: 2.1
Name: transaction-indexer-quality-checker
Version: 0.0.2
Summary: Transaction indexer quality checker
Home-page: https://github.com/keyperlabs/transaction-indexer-quality-checker.git
Author: Palmera
Author-email: general@palmeradao.xyz
